runexpy/__about__.py
runexpy/__init__.py
runexpy/campaign.py
runexpy/database.py
runexpy/result.py
runexpy/runner.py
runexpy/utils.py
runexpy-0.1.1.dist-info/METADATA
runexpy-0.1.1.dist-info/WHEEL
runexpy-0.1.1.dist-info/licenses/LICENSE
runexpy-0.1.1.dist-info/RECORD
