Metadata-Version: 2.1
Name: runexpy
Version: 0.1.1
Summary: Python experiment manager
Project-URL: Documentation, https://github.com/masinag/runexpy#readme
Project-URL: Issues, https://github.com/masinag/runexpy/issues
Project-URL: Source, https://github.com/masinag/runexpy
Author-email: Gabriele Masina <gabriele.masina@virgilio.it>
Classifier: Development Status :: 4 - Beta
Classifier: Programming Language :: Python
Classifier: Programming Language :: Python :: 3.7
Classifier: Programming Language :: Python :: 3.8
Classifier: Programming Language :: Python :: 3.9
Classifier: Programming Language :: Python :: 3.10
Classifier: Programming Language :: Python :: 3.11
Classifier: Programming Language :: Python :: Implementation :: CPython
Classifier: Programming Language :: Python :: Implementation :: PyPy
Requires-Python: >=3.7
Requires-Dist: tinydb
Requires-Dist: typing-extensions
Provides-Extra: dev
Requires-Dist: black; extra == 'dev'
Requires-Dist: flake8; extra == 'dev'
Requires-Dist: isort; extra == 'dev'
Provides-Extra: example
Requires-Dist: matplotlib; extra == 'example'
Requires-Dist: numpy; extra == 'example'
Provides-Extra: test
Requires-Dist: pytest; extra == 'test'
